pysslcommerz/__init__.py
pysslcommerz/sslcommerz.py
pysslcommerz-1.3.dist-info/METADATA
pysslcommerz-1.3.dist-info/WHEEL
pysslcommerz-1.3.dist-info/licenses/LICENSE
pysslcommerz-1.3.dist-info/RECORD
