Metadata-Version: 2.4
Name: pysslcommerz
Version: 1.3
Summary: Python client for SSLcommerz. Forked from official client.
Author-email: SSLCOMMERZ Developers <sajan.sslwireless@gmail.com>, rozari0 <rozario@duck.com>
License-File: LICENSE
Requires-Python: >=3.9
Requires-Dist: requests
